ctms/binutils/__init__.py
ctms/binutils/binutils.dll
ctms/binutils/binutils.py
ctms/binutils/clib.py
ctms/binutils/coff/__init__.py
ctms/binutils/coff/coff_obj.py
ctms/binutils/coff/coff_sect.py
ctms_binutils-0.1.0.dist-info/METADATA
ctms_binutils-0.1.0.dist-info/WHEEL
ctms_binutils-0.1.0.dist-info/top_level.txt
ctms_binutils-0.1.0.dist-info/RECORD
