Metadata-Version: 2.1
Name: ctms-binutils
Version: 0.1.0
Summary: Binary utilities for working with embedded object files
Author-email: Colton Murphy <cmurp77@gmail.com>
Classifier: Programming Language :: Python :: 3
Classifier: Operating System :: Microsoft :: Windows :: Windows 10
Requires-Python: >=3.12
